{
"type": "FeatureCollection",
"name": "beijing-daxing-airport-express-phase-1-stops",
"crs": { "type": "name", "properties": { "name": "urn:ogc:def:crs:OGC:1.3:CRS84" } },
"features": [
{ "type": "Feature", "properties": { "full_id": "", "osm_id": null, "osm_type": null, "name": "Daxingxincheng", "name:en": "Daxingxincheng", "name:zh": "大兴新城", "public_transport": null, "railway": null, "subway": null, "name:ru": null, "barrier": null, "wikidata": null, "wikipedia:zh": null, "name:es": null, "name:de": null, "name:zh-Hans": null, "name:zh-Hant": null, "name:zh_pinyin": null, "name:hu": null, "name:ja": null, "network": null, "highway": null, "station": null, "train": null, "uic_ref": null, "wheelchair": null, "access": null, "description": null, "ref": null, "alt_name": null, "int_name": null, "name:pl": null, "level": null, "crossing": null, "bus": null, "departures_board": null, "shelter": null }, "geometry": { "type": "Point", "coordinates": [ 116.359811587311668, 39.725865639985237 ] } },
{ "type": "Feature", "properties": { "full_id": "n6841358403", "osm_id": "6841358403", "osm_type": "node", "name": "Caoqiao", "name:en": "Caoqiao", "name:zh": "草桥", "public_transport": "stop_position", "railway": "", "subway": "yes", "name:ru": "", "barrier": "", "wikidata": "Q2257617", "wikipedia:zh": "", "name:es": "", "name:de": "", "name:zh-Hans": "", "name:zh-Hant": "", "name:zh_pinyin": "Căoqiáo", "name:hu": "", "name:ja": "", "network": "", "highway": "", "station": "", "train": "", "uic_ref": "", "wheelchair": "", "access": "", "description": "", "ref": "", "alt_name": "", "int_name": "", "name:pl": "", "level": "", "crossing": "", "bus": "", "departures_board": "", "shelter": "" }, "geometry": { "type": "Point", "coordinates": [ 116.3424817, 39.8461302 ] } },
{ "type": "Feature", "properties": { "full_id": "n7119001898", "osm_id": "7119001898", "osm_type": "node", "name": "Daxing Airport", "name:en": "Daxing Airport", "name:zh": "大兴机场", "public_transport": "stop_position", "railway": "", "subway": "yes", "name:ru": "", "barrier": "", "wikidata": "", "wikipedia:zh": "", "name:es": "", "name:de": "", "name:zh-Hans": "", "name:zh-Hant": "", "name:zh_pinyin": "", "name:hu": "", "name:ja": "", "network": "", "highway": "", "station": "", "train": "", "uic_ref": "", "wheelchair": "", "access": "", "description": "", "ref": "", "alt_name": "", "int_name": "", "name:pl": "", "level": "", "crossing": "", "bus": "", "departures_board": "", "shelter": "" }, "geometry": { "type": "Point", "coordinates": [ 116.4106342, 39.5124877 ] } }
]
}
