{
"type": "FeatureCollection",
"name": "beijing-line-8-phase-1-for-olympics-stops",
"crs": { "type": "name", "properties": { "name": "urn:ogc:def:crs:OGC:1.3:CRS84" } },
"features": [
{ "type": "Feature", "properties": { "full_id": "n1352161814", "osm_id": "1352161814", "osm_type": "node", "name": "Olympic Sports Center", "name:en": "Olympic Sports Center", "name:zh": "奥体中心", "public_transport": "stop_position", "railway": "stop", "subway": "yes", "name:ru": "", "barrier": "", "wikidata": "", "wikipedia:zh": "", "name:es": "", "name:de": "", "name:zh-Hans": "", "name:zh-Hant": "", "name:zh_pinyin": "", "name:hu": "", "name:ja": "", "network": "", "highway": "", "station": "", "train": "", "uic_ref": "", "wheelchair": "", "access": "", "description": "", "ref": "", "alt_name": "", "int_name": "", "name:pl": "", "level": "", "crossing": "", "bus": "", "departures_board": "", "shelter": "" }, "geometry": { "type": "Point", "coordinates": [ 116.3876868, 39.9841376 ] } },
{ "type": "Feature", "properties": { "full_id": "n1352161813", "osm_id": "1352161813", "osm_type": "node", "name": "Beitucheng", "name:en": "Beitucheng", "name:zh": "北土城", "public_transport": "stop_position", "railway": "stop", "subway": "yes", "name:ru": "", "barrier": "", "wikidata": "", "wikipedia:zh": "", "name:es": "", "name:de": "", "name:zh-Hans": "", "name:zh-Hant": "", "name:zh_pinyin": "", "name:hu": "", "name:ja": "", "network": "", "highway": "", "station": "", "train": "", "uic_ref": "", "wheelchair": "", "access": "", "description": "", "ref": "", "alt_name": "", "int_name": "", "name:pl": "", "level": "", "crossing": "", "bus": "", "departures_board": "", "shelter": "" }, "geometry": { "type": "Point", "coordinates": [ 116.3880571, 39.9764013 ] } },
{ "type": "Feature", "properties": { "full_id": "n339097485", "osm_id": "339097485", "osm_type": "node", "name": "South Gate of Forest Park", "name:en": "South Gate of Forest Park", "name:zh": "森林公园南门", "public_transport": "stop_position", "railway": "", "subway": "yes", "name:ru": "", "barrier": "", "wikidata": "", "wikipedia:zh": "", "name:es": "", "name:de": "", "name:zh-Hans": "", "name:zh-Hant": "", "name:zh_pinyin": "", "name:hu": "", "name:ja": "", "network": "", "highway": "", "station": "", "train": "", "uic_ref": "", "wheelchair": "", "access": "", "description": "", "ref": "", "alt_name": "", "int_name": "", "name:pl": "", "level": "", "crossing": "", "bus": "", "departures_board": "", "shelter": "" }, "geometry": { "type": "Point", "coordinates": [ 116.3862915, 40.0091958 ] } },
{ "type": "Feature", "properties": { "full_id": "n339097239", "osm_id": "339097239", "osm_type": "node", "name": "Olympic Green", "name:en": "Olympic Green", "name:zh": "", "public_transport": "stop_position", "railway": "", "subway": "yes", "name:ru": "", "barrier": "", "wikidata": "", "wikipedia:zh": "", "name:es": "", "name:de": "", "name:zh-Hans": "", "name:zh-Hant": "", "name:zh_pinyin": "", "name:hu": "", "name:ja": "", "network": "", "highway": "", "station": "", "train": "", "uic_ref": "", "wheelchair": "", "access": "", "description": "", "ref": "", "alt_name": "", "int_name": "", "name:pl": "", "level": "", "crossing": "", "bus": "", "departures_board": "", "shelter": "" }, "geometry": { "type": "Point", "coordinates": [ 116.386751, 39.999324 ] } }
]
}
