{
"type": "FeatureCollection",
"name": "beijing-line-8-phase-3-north-stops",
"crs": { "type": "name", "properties": { "name": "urn:ogc:def:crs:OGC:1.3:CRS84" } },
"features": [
{ "type": "Feature", "properties": { "full_id": null, "osm_id": null, "osm_type": null, "name": "Wangfujing North", "name:en": "Wangfujing North", "public_transport": null, "railway": null, "subway": null, "ref": null, "construction": null, "construction:public_transport": null, "station": null, "wikidata": null, "wikipedia:zh": null, "name:zh": null, "monorail": null, "train": null, "description": null, "railway:construction": null }, "geometry": { "type": "Point", "coordinates": [ 116.404633854378076, 39.921792942157339 ] } },
{ "type": "Feature", "properties": { "full_id": null, "osm_id": null, "osm_type": null, "name": "Wangfujing", "name:en": "Wangfujing", "public_transport": null, "railway": null, "subway": null, "ref": null, "construction": null, "construction:public_transport": null, "station": null, "wikidata": null, "wikipedia:zh": null, "name:zh": null, "monorail": null, "train": null, "description": null, "railway:construction": null }, "geometry": { "type": "Point", "coordinates": [ 116.405393495259418, 39.907518023928894 ] } },
{ "type": "Feature", "properties": { "full_id": null, "osm_id": null, "osm_type": null, "name": "Qianmen", "name:en": "Qianmen", "public_transport": null, "railway": null, "subway": null, "ref": null, "construction": null, "construction:public_transport": null, "station": null, "wikidata": null, "wikipedia:zh": null, "name:zh": null, "monorail": null, "train": null, "description": null, "railway:construction": null }, "geometry": { "type": "Point", "coordinates": [ 116.391846566208926, 39.897294523734232 ] } }
]
}
