{
"type": "FeatureCollection",
"name": "lodz-cross-city-line-stops",
"crs": { "type": "name", "properties": { "name": "urn:ogc:def:crs:OGC:1.3:CRS84" } },
"features": [
{ "type": "Feature", "properties": { "full_id": "n1537305330", "osm_id": "1537305330", "osm_type": "node", "railway": "proposed", "ref": "", "source:ref": "", "name": "Łódź Śródmieście", "public_transport": "", "train": "", "crossing:barrier": "", "crossing:supervision": "", "level": "-3", "proposed": "halt", "barrier": "", "tram": "", "layer": "", "disused:public_transport": "", "disused:railway": "", "wheelchair": "", "crossing": "", "crossing:island": "", "highway": "", "website": "", "bench": "", "covered": "", "crossing:light": "", "supervised": "", "crossing:saltire": "", "bicycle": "", "name:ru": "", "name:uk": "", "operator": "", "railway:ref:DB": "", "wikidata": "", "wikipedia": "", "button_operated": "", "tactile_paving": "", "traffic_signals:sound": "", "traffic_signals:vibration": "", "entrance": "", "email": "", "image": "", "platforms": "", "reg_name": "", "toilets:wheelchair": "", "url": "", "historic": "", "locomotive:type": "", "access": "", "horse": "", "motor_vehicle": "", "noexit": "", "disused": "", "internet_access": "", "start_date": "", "proposed:public_transport": "", "proposed:railway": "" }, "geometry": { "type": "Point", "coordinates": [ 19.4524337, 51.7704655 ] } },
{ "type": "Feature", "properties": { "full_id": "n4427050629", "osm_id": "4427050629", "osm_type": "node", "railway": "proposed", "ref": "", "source:ref": "", "name": "Łódź Polesie", "public_transport": "", "train": "", "crossing:barrier": "", "crossing:supervision": "", "level": "-3", "proposed": "halt", "barrier": "", "tram": "", "layer": "", "disused:public_transport": "", "disused:railway": "", "wheelchair": "", "crossing": "", "crossing:island": "", "highway": "", "website": "", "bench": "", "covered": "", "crossing:light": "", "supervised": "", "crossing:saltire": "", "bicycle": "", "name:ru": "", "name:uk": "", "operator": "", "railway:ref:DB": "", "wikidata": "", "wikipedia": "", "button_operated": "", "tactile_paving": "", "traffic_signals:sound": "", "traffic_signals:vibration": "", "entrance": "", "email": "", "image": "", "platforms": "", "reg_name": "", "toilets:wheelchair": "", "url": "", "historic": "", "locomotive:type": "", "access": "", "horse": "", "motor_vehicle": "", "noexit": "", "disused": "", "internet_access": "", "start_date": "", "proposed:public_transport": "", "proposed:railway": "" }, "geometry": { "type": "Point", "coordinates": [ 19.4417777, 51.7771027 ] } }
]
}
