{
"type": "FeatureCollection",
"name": "madrid-line-9-extension-stops",
"crs": { "type": "name", "properties": { "name": "urn:ogc:def:crs:OGC:1.3:CRS84" } },
"features": [
{ "type": "Feature", "properties": { "full_id": "n1430344237", "osm_id": "1430344237", "osm_type": "node", "covered": "yes", "fare_area": "A", "name": "Mirasierra", "operator": "Metro de Madrid", "public_transport": "stop_position", "railway": "stop", "subway": "yes", "wheelchair": "yes", "colour": "#9F1F99", "network": "Metro de Madrid", "toilets:wheelchair": "", "wikidata": "", "wikipedia": "", "layer": "", "source:name": "", "wheelchair:description": "", "station": "", "addr:city": "", "addr:country": "", "url": "", "crossing": "", "highway": "", "bicycle": "", "train": "", "traffic_signals": "", "name:ar": "", "name:es": "", "internet_access": "", "type": "", "website": "", "alt_name": "", "source:date": "", "level": "", "name:pt": "", "addr:housenumber": "", "addr:street": "", "entrance": "", "barrier": "" }, "geometry": { "type": "Point", "coordinates": [ -3.7166613, 40.4912608 ] } },
{ "type": "Feature", "properties": { "full_id": "n2575149571", "osm_id": "2575149571", "osm_type": "node", "covered": "yes", "fare_area": "A", "name": "Paco de Lucía", "operator": "Metro de Madrid", "public_transport": "stop_position", "railway": "stop", "subway": "yes", "wheelchair": "yes", "colour": "#000000", "network": "Metro de Madrid", "toilets:wheelchair": "", "wikidata": "", "wikipedia": "", "layer": "", "source:name": "", "wheelchair:description": "", "station": "", "addr:city": "", "addr:country": "", "url": "", "crossing": "", "highway": "", "bicycle": "", "train": "", "traffic_signals": "", "name:ar": "", "name:es": "", "internet_access": "", "type": "", "website": "", "alt_name": "", "source:date": "", "level": "", "name:pt": "", "addr:housenumber": "", "addr:street": "", "entrance": "", "barrier": "" }, "geometry": { "type": "Point", "coordinates": [ -3.7093378, 40.4996143 ] } },
{ "type": "Feature", "properties": { "full_id": "n5307426097", "osm_id": "5307426097", "osm_type": "node", "covered": "yes", "fare_area": "A", "name": "Paco de Lucía", "operator": "Metro de Madrid", "public_transport": "stop_position", "railway": "stop", "subway": "yes", "wheelchair": "yes", "colour": "#000000", "network": "Metro de Madrid", "toilets:wheelchair": "", "wikidata": "", "wikipedia": "", "layer": "", "source:name": "", "wheelchair:description": "", "station": "", "addr:city": "", "addr:country": "", "url": "", "crossing": "", "highway": "", "bicycle": "", "train": "", "traffic_signals": "", "name:ar": "", "name:es": "", "internet_access": "", "type": "", "website": "", "alt_name": "", "source:date": "", "level": "", "name:pt": "", "addr:housenumber": "", "addr:street": "", "entrance": "", "barrier": "" }, "geometry": { "type": "Point", "coordinates": [ -3.709367, 40.4996559 ] } },
{ "type": "Feature", "properties": { "full_id": "n5307435828", "osm_id": "5307435828", "osm_type": "node", "covered": "yes", "fare_area": "A", "name": "Mirasierra", "operator": "Metro de Madrid", "public_transport": "stop_position", "railway": "stop", "subway": "yes", "wheelchair": "yes", "colour": "#9F1F99", "network": "Metro de Madrid", "toilets:wheelchair": "", "wikidata": "", "wikipedia": "", "layer": "", "source:name": "", "wheelchair:description": "", "station": "", "addr:city": "", "addr:country": "", "url": "", "crossing": "", "highway": "", "bicycle": "", "train": "", "traffic_signals": "", "name:ar": "", "name:es": "", "internet_access": "", "type": "", "website": "", "alt_name": "", "source:date": "", "level": "", "name:pt": "", "addr:housenumber": "", "addr:street": "", "entrance": "", "barrier": "" }, "geometry": { "type": "Point", "coordinates": [ -3.7167771, 40.4911747 ] } }
]
}
