{
"type": "FeatureCollection",
"name": "beijing-line-8-northern-extension-stops",
"crs": { "type": "name", "properties": { "name": "urn:ogc:def:crs:OGC:1.3:CRS84" } },
"features": [
{ "type": "Feature", "properties": { "full_id": "n3057144414", "osm_id": "3057144414", "osm_type": "node", "name": "Yuzhilu", "name:en": "Yuzhilu", "name:zh": "育知路", "public_transport": "stop_position", "railway": "", "subway": "yes", "name:ru": "", "barrier": "", "wikidata": "", "wikipedia:zh": "", "name:es": "", "name:de": "", "name:zh-Hans": "", "name:zh-Hant": "", "name:zh_pinyin": "", "name:hu": "", "name:ja": "", "network": "", "highway": "", "station": "", "train": "", "uic_ref": "", "wheelchair": "", "access": "", "description": "", "ref": "", "alt_name": "", "int_name": "", "name:pl": "", "level": "", "crossing": "", "bus": "", "departures_board": "", "shelter": "" }, "geometry": { "type": "Point", "coordinates": [ 116.3204368, 40.0865428 ] } },
{ "type": "Feature", "properties": { "full_id": "n3057104138", "osm_id": "3057104138", "osm_type": "node", "name": "Zhuxinzhuang", "name:en": "Zhuxinzhuang", "name:zh": "朱辛庄", "public_transport": "stop_position", "railway": "stop", "subway": "yes", "name:ru": "", "barrier": "", "wikidata": "", "wikipedia:zh": "", "name:es": "", "name:de": "", "name:zh-Hans": "", "name:zh-Hant": "", "name:zh_pinyin": "", "name:hu": "", "name:ja": "", "network": "", "highway": "", "station": "", "train": "", "uic_ref": "", "wheelchair": "", "access": "", "description": "", "ref": "", "alt_name": "", "int_name": "", "name:pl": "", "level": "", "crossing": "", "bus": "", "departures_board": "", "shelter": "" }, "geometry": { "type": "Point", "coordinates": [ 116.3075674, 40.103004 ] } },
{ "type": "Feature", "properties": { "full_id": null, "osm_id": null, "osm_type": null, "name": "PingxiFu", "name:en": "Pingxifu", "name:zh": null, "public_transport": null, "railway": null, "subway": null, "name:ru": null, "barrier": null, "wikidata": null, "wikipedia:zh": null, "name:es": null, "name:de": null, "name:zh-Hans": null, "name:zh-Hant": null, "name:zh_pinyin": null, "name:hu": null, "name:ja": null, "network": null, "highway": null, "station": null, "train": null, "uic_ref": null, "wheelchair": null, "access": null, "description": null, "ref": null, "alt_name": null, "int_name": null, "name:pl": null, "level": null, "crossing": null, "bus": null, "departures_board": null, "shelter": null }, "geometry": { "type": "Point", "coordinates": [ 116.344159845204288, 40.088618868712381 ] } }
]
}
