{
"type": "FeatureCollection",
"name": "changsha-line-5-south-extension-stops",
"crs": { "type": "name", "properties": { "name": "urn:ogc:def:crs:OGC:1.3:CRS84" } },
"features": [
{ "type": "Feature", "properties": { "full_id": null, "osm_id": null, "osm_type": null, "name": "Name not decided", "name:en": null, "public_transport": null, "railway": null, "station": null, "subway": null, "wikidata": null, "access": null, "description": null }, "geometry": { "type": "Point", "coordinates": [ 113.030069565277984, 28.086861468537865 ] } },
{ "type": "Feature", "properties": { "full_id": null, "osm_id": null, "osm_type": null, "name": "Name not decided", "name:en": null, "public_transport": null, "railway": null, "station": null, "subway": null, "wikidata": null, "access": null, "description": null }, "geometry": { "type": "Point", "coordinates": [ 113.017277747431748, 28.07875187027205 ] } },
{ "type": "Feature", "properties": { "full_id": null, "osm_id": null, "osm_type": null, "name": "Name not decided", "name:en": null, "public_transport": null, "railway": null, "station": null, "subway": null, "wikidata": null, "access": null, "description": null }, "geometry": { "type": "Point", "coordinates": [ 113.007541391571976, 28.078334597878055 ] } },
{ "type": "Feature", "properties": { "full_id": null, "osm_id": null, "osm_type": null, "name": "Name not decided", "name:en": null, "public_transport": null, "railway": null, "station": null, "subway": null, "wikidata": null, "access": null, "description": null }, "geometry": { "type": "Point", "coordinates": [ 112.991792382411816, 28.076370696284613 ] } },
{ "type": "Feature", "properties": { "full_id": null, "osm_id": null, "osm_type": null, "name": "Name not decided", "name:en": null, "public_transport": null, "railway": null, "station": null, "subway": null, "wikidata": null, "access": null, "description": null }, "geometry": { "type": "Point", "coordinates": [ 112.984006321436937, 28.07636389293036 ] } },
{ "type": "Feature", "properties": { "full_id": null, "osm_id": null, "osm_type": null, "name": "Name not decided", "name:en": null, "public_transport": null, "railway": null, "station": null, "subway": null, "wikidata": null, "access": null, "description": null }, "geometry": { "type": "Point", "coordinates": [ 112.978278653086818, 28.076303418670378 ] } },
{ "type": "Feature", "properties": { "full_id": null, "osm_id": null, "osm_type": null, "name": "Name not decided", "name:en": null, "public_transport": null, "railway": null, "station": null, "subway": null, "wikidata": null, "access": null, "description": null }, "geometry": { "type": "Point", "coordinates": [ 112.967790904546547, 28.076218754706392 ] } }
]
}
