{
"type": "FeatureCollection",
"name": "london-battersea-stops",
"crs": { "type": "name", "properties": { "name": "urn:ogc:def:crs:OGC:1.3:CRS84" } },
"features": [
{ "type": "Feature", "properties": { "full_id": null, "osm_id": null, "osm_type": null, "name": "Nine Elms", "operator": null, "public_transport": null, "railway": null, "subway": null, "line": "NLE", "network": null, "name:ru": null, "ref": null, "wheelchair": null, "fare_zone": null, "platforms": null, "station": null, "train": null, "wikidata": null, "wikipedia": null, "level": null, "wikimedia_commons": null, "layer": null, "name:da": null, "destination": null, "electrified": null, "frequency": null, "voltage": null, "bus": null, "departures_board": null, "highway": null, "local_ref": null, "naptan:AtcoCode": null, "naptan:Bearing": null, "naptan:CommonName": null, "naptan:Indicator": null, "naptan:Street": null, "naptan:verified": null, "shelter": null, "tactile_paving": null, "lcn": null, "crossing": null, "crossing_ref": null, "noexit": null, "zone": null, "old_name": null, "source_ref": null, "disused": null, "railway:switch": null, "railway:turnout_side": null, "disused:railway": null, "ref:tiploc": null, "wheelchair:description": null, "public_transport:version": null, "barrier": null, "description": null, "crossing:barrier": null, "source:level": null, "amenity": null, "button_operated": null, "crossing:island": null, "kerb": null, "traffic_signals": null, "traffic_signals:direction": null, "media:commons": null, "source:name": null }, "geometry": { "type": "Point", "coordinates": [ -0.1285399135644, 51.479883053012792 ] } },
{ "type": "Feature", "properties": { "full_id": null, "osm_id": null, "osm_type": null, "name": "Battersea Power Station", "operator": null, "public_transport": null, "railway": null, "subway": null, "line": "NLE", "network": null, "name:ru": null, "ref": null, "wheelchair": null, "fare_zone": null, "platforms": null, "station": null, "train": null, "wikidata": null, "wikipedia": null, "level": null, "wikimedia_commons": null, "layer": null, "name:da": null, "destination": null, "electrified": null, "frequency": null, "voltage": null, "bus": null, "departures_board": null, "highway": null, "local_ref": null, "naptan:AtcoCode": null, "naptan:Bearing": null, "naptan:CommonName": null, "naptan:Indicator": null, "naptan:Street": null, "naptan:verified": null, "shelter": null, "tactile_paving": null, "lcn": null, "crossing": null, "crossing_ref": null, "noexit": null, "zone": null, "old_name": null, "source_ref": null, "disused": null, "railway:switch": null, "railway:turnout_side": null, "disused:railway": null, "ref:tiploc": null, "wheelchair:description": null, "public_transport:version": null, "barrier": null, "description": null, "crossing:barrier": null, "source:level": null, "amenity": null, "button_operated": null, "crossing:island": null, "kerb": null, "traffic_signals": null, "traffic_signals:direction": null, "media:commons": null, "source:name": null }, "geometry": { "type": "Point", "coordinates": [ -0.14207101795195, 51.479871733336005 ] } }
]
}
