{
"type": "FeatureCollection",
"name": "nanjing-line-2-western-extension-stops",
"crs": { "type": "name", "properties": { "name": "urn:ogc:def:crs:OGC:1.3:CRS84" } },
"features": [
{ "type": "Feature", "properties": { "full_id": "n5124587787", "osm_id": "5124587787", "osm_type": "node", "name": "Yuzui", "name:en": "Yuzui", "railway": "construction", "station": "subway", "highway": "", "construction": "station", "subway": "yes", "public_transport": "" }, "geometry": { "type": "Point", "coordinates": [ 118.6633944, 31.96909 ] } },
{ "type": "Feature", "properties": { "full_id": "n5124587791", "osm_id": "5124587791", "osm_type": "node", "name": "Tainbaojie", "name:en": "Tainbaojie", "railway": "construction", "station": "subway", "highway": "", "construction": "station", "subway": "yes", "public_transport": "" }, "geometry": { "type": "Point", "coordinates": [ 118.6748316, 31.9677774 ] } },
{ "type": "Feature", "properties": { "full_id": "n5124587792", "osm_id": "5124587792", "osm_type": "node", "name": "Qinglainjie", "name:en": "Qinglainjie", "railway": "construction", "station": "subway", "highway": "", "construction": "station", "subway": "", "public_transport": "" }, "geometry": { "type": "Point", "coordinates": [ 118.68456, 31.9647085 ] } },
{ "type": "Feature", "properties": { "full_id": "n5124587796", "osm_id": "5124587796", "osm_type": "node", "name": "Luotangjie", "name:en": "Luotangjie", "railway": "construction", "station": "subway", "highway": "", "construction": "station", "subway": "", "public_transport": "" }, "geometry": { "type": "Point", "coordinates": [ 118.696609, 31.9627195 ] } }
]
}
