{
"type": "FeatureCollection",
"name": "perth-forrestfield-airport-link-stops",
"crs": { "type": "name", "properties": { "name": "urn:ogc:def:crs:OGC:1.3:CRS84" } },
"features": [
{ "type": "Feature", "properties": { "full_id": "n5601025495", "osm_id": "5601025495", "osm_type": "node", "railway": "construction", "crossing:barrier": "", "disused:public_transport": "", "disused:railway": "", "name": "Airport Central", "train": "", "wikidata": "Q19818501", "wikipedia": "en:Airport Central railway station", "crossing:bell": "", "crossing:light": "", "operator": "Transperth", "public_transport": "station", "addr:postcode": "", "addr:state": "", "addr:suburb": "", "internet_access": "", "layer": "", "level": "", "bicycle": "", "crossing": "", "usage": "", "network": "", "attribution": "", "barrier": "", "foot": "", "horse": "", "noexit": "", "highway": "", "entrance": "", "addr:city": "", "addr:housenumber": "", "addr:street": "", "station": "subway", "subway": "", "wheelchair": "", "location": "", "crossing:supervision": "", "crane:note": "", "crane:type": "", "man_made": "", "ref": "", "historic:railway": "", "official_name": "", "construction": "station", "traffic_calming": "", "traffic_signals": "", "local_ref": "" }, "geometry": { "type": "Point", "coordinates": [ 115.9749024, -31.9439543 ] } },
{ "type": "Feature", "properties": { "full_id": "n5601025496", "osm_id": "5601025496", "osm_type": "node", "railway": "construction", "crossing:barrier": "", "disused:public_transport": "", "disused:railway": "", "name": "High Wycombe", "train": "", "wikidata": "Q19818500", "wikipedia": "en:High Wycombe railway station, Perth", "crossing:bell": "", "crossing:light": "", "operator": "Transperth", "public_transport": "station", "addr:postcode": "", "addr:state": "", "addr:suburb": "", "internet_access": "", "layer": "", "level": "", "bicycle": "", "crossing": "", "usage": "", "network": "", "attribution": "", "barrier": "", "foot": "", "horse": "", "noexit": "", "highway": "", "entrance": "", "addr:city": "", "addr:housenumber": "", "addr:street": "", "station": "", "subway": "", "wheelchair": "", "location": "", "crossing:supervision": "", "crane:note": "", "crane:type": "", "man_made": "", "ref": "", "historic:railway": "", "official_name": "", "construction": "station", "traffic_calming": "", "traffic_signals": "", "local_ref": "" }, "geometry": { "type": "Point", "coordinates": [ 115.9922046, -31.9546594 ] } },
{ "type": "Feature", "properties": { "full_id": "n5601025492", "osm_id": "5601025492", "osm_type": "node", "railway": "construction", "crossing:barrier": "", "disused:public_transport": "", "disused:railway": "", "name": "Redcliffe", "train": "", "wikidata": "Q52776430", "wikipedia": "", "crossing:bell": "", "crossing:light": "", "operator": "Transperth", "public_transport": "station", "addr:postcode": "", "addr:state": "", "addr:suburb": "", "internet_access": "", "layer": "", "level": "", "bicycle": "", "crossing": "", "usage": "", "network": "", "attribution": "", "barrier": "", "foot": "", "horse": "", "noexit": "", "highway": "", "entrance": "", "addr:city": "", "addr:housenumber": "", "addr:street": "", "station": "", "subway": "", "wheelchair": "", "location": "", "crossing:supervision": "", "crane:note": "", "crane:type": "", "man_made": "", "ref": "", "historic:railway": "", "official_name": "", "construction": "station", "traffic_calming": "", "traffic_signals": "", "local_ref": "" }, "geometry": { "type": "Point", "coordinates": [ 115.9497086, -31.93359 ] } }
]
}
