{
"type": "FeatureCollection",
"name": "shenzhen-line-8-phase-2-stops",
"crs": { "type": "name", "properties": { "name": "urn:ogc:def:crs:OGC:1.3:CRS84" } },
"features": [
{ "type": "Feature", "properties": { "full_id": "n4488729590", "osm_id": "4488729590", "osm_type": "node", "name": "Yantian Food Street", "name:en": "Yantian Food Street", "proposed": "", "railway": "construction", "name:zh": "盐田食街", "public_transport": "", "station": "", "train": "", "construction": "station", "network": "", "operator": "", "subway": "", "wikidata": "", "platforms": "", "public_transport:proposed": "" }, "geometry": { "type": "Point", "coordinates": [ 114.2755529, 22.5903123 ] } },
{ "type": "Feature", "properties": { "full_id": "n6673778487", "osm_id": "6673778487", "osm_type": "node", "name": "Xiaomeisha", "name:en": "Xiaomeisha", "proposed": "", "railway": "", "name:zh": "小梅沙", "public_transport": "stop_position", "station": "", "train": "", "construction": "station", "network": "", "operator": "", "subway": "", "wikidata": "", "platforms": "", "public_transport:proposed": "" }, "geometry": { "type": "Point", "coordinates": [ 114.3219626, 22.6041888 ] } },
{ "type": "Feature", "properties": { "full_id": null, "osm_id": null, "osm_type": null, "name": "Beishan Street", "name:en": "Beishan Street", "proposed": null, "railway": null, "name:zh": null, "public_transport": null, "station": null, "train": null, "construction": null, "network": null, "operator": null, "subway": null, "wikidata": null, "platforms": null, "public_transport:proposed": null }, "geometry": { "type": "Point", "coordinates": [ 114.259884158128642, 22.593602747989717 ] } },
{ "type": "Feature", "properties": { "full_id": "n6673770827", "osm_id": "6673770827", "osm_type": "node", "name": "Dameisha", "name:en": "Dameisha", "proposed": "", "railway": "", "name:zh": "大梅沙", "public_transport": "stop_position", "station": "", "train": "", "construction": "station", "network": "", "operator": "", "subway": "", "wikidata": "", "platforms": "", "public_transport:proposed": "" }, "geometry": { "type": "Point", "coordinates": [ 114.3047827, 22.5989022 ] } }
]
}
