{
"type": "FeatureCollection",
"name": "turin-line-1-south-phase-4-stops",
"crs": { "type": "name", "properties": { "name": "urn:ogc:def:crs:OGC:1.3:CRS84" } },
"features": [
{ "type": "Feature", "properties": { "full_id": "n6257614746", "osm_id": "6257614746", "osm_type": "node", "highway": "", "traffic_signals": "", "barrier": "", "material": "", "railway": "station", "comments": "", "traffic_signals:sound": "", "traffic_signals:direction": "", "gtfs_id": "", "name": "Bengasi", "public_transport": "stop_position", "train": "", "crossing": "", "tactile_paving": "", "operator": "Gruppo Torinese Trasporti", "ref": "", "station": "subway", "subway": "yes", "wheelchair": "", "wikidata": "", "wikipedia": "", "start_date": "", "bicycle": "", "colour": "", "check_date:wheelchair": "", "emergency": "", "GTT:Revised": "", "shelter": "", "bench": "", "addr:city": "", "addr:street": "", "button_operated": "", "crossing:island": "", "traffic_signals:vibration": "", "tram": "", "toilets:wheelchair": "", "layer": "", "network": "", "alt_name": "", "short_name": "", "crossing_ref": "", "direction": "", "local_ref": "", "foot": "", "addr:housenumber": "", "kerb": "", "motorcar": "", "covered": "", "bus": "", "key": "", "entrance": "", "traffic_sign": "", "defibrillator": "", "bridge:support": "", "amenity": "", "disabled": "", "crossing:barrier": "" }, "geometry": { "type": "Point", "coordinates": [ 7.6613021, 45.0169671 ] } },
{ "type": "Feature", "properties": { "full_id": "n6257614747", "osm_id": "6257614747", "osm_type": "node", "highway": "", "traffic_signals": "", "barrier": "", "material": "", "railway": "station", "comments": "", "traffic_signals:sound": "", "traffic_signals:direction": "", "gtfs_id": "", "name": "Italia '61 - Regione Piemonte", "public_transport": "stop_position", "train": "", "crossing": "", "tactile_paving": "", "operator": "Gruppo Torinese Trasporti", "ref": "", "station": "", "subway": "yes", "wheelchair": "", "wikidata": "", "wikipedia": "", "start_date": "", "bicycle": "", "colour": "", "check_date:wheelchair": "", "emergency": "", "GTT:Revised": "", "shelter": "", "bench": "", "addr:city": "", "addr:street": "", "button_operated": "", "crossing:island": "", "traffic_signals:vibration": "", "tram": "", "toilets:wheelchair": "", "layer": "", "network": "Formula", "alt_name": "", "short_name": "", "crossing_ref": "", "direction": "", "local_ref": "", "foot": "", "addr:housenumber": "", "kerb": "", "motorcar": "", "covered": "", "bus": "", "key": "", "entrance": "", "traffic_sign": "", "defibrillator": "", "bridge:support": "", "amenity": "", "disabled": "", "crossing:barrier": "" }, "geometry": { "type": "Point", "coordinates": [ 7.6642899, 45.0246783 ] } }
]
}
