{
"type": "FeatureCollection",
"name": "seoul-line-7-extension-stops",
"crs": { "type": "name", "properties": { "name": "urn:ogc:def:crs:OGC:1.3:CRS84" } },
"features": [
{ "type": "Feature", "properties": { "full_id": "n8754538369", "osm_id": "8754538369", "osm_type": "node", "name": "석남", "name:ko": "석남", "operator": "인천교통공사", "public_transport": "stop_position", "railway": "stop", "ref": "761", "subway": "yes", "name:en": "Seongnam", "name:ja": "", "station": "", "wikidata": "", "wikipedia": "", "wheelchair": "", "train": "", "name:zh": "", "local_ref": "", "alt_name": "", "alt_name:en": "", "network": "", "addr:city": "", "addr:housenumber": "", "addr:street": "", "internet_access": "", "full_name": "", "bicycle": "", "description": "", "description:en": "", "light_rail": "", "name:ko-Latn": "", "tag": "", "alt_name:ko": "", "description:ja": "", "description:zh": "", "operator:en": "", "start_date": "2021-05-22", "layer": "", "loc_name": "", "construction": "", "platforms": "", "railway:signal:direction": "", "construction:railway": "" }, "geometry": { "type": "Point", "coordinates": [ 126.674636033676364, 37.506268951761776 ] } },
{ "type": "Feature", "properties": { "full_id": "n8754538368", "osm_id": "8754538368", "osm_type": "node", "name": "석남", "name:ko": "석남", "operator": "인천교통공사", "public_transport": "stop_position", "railway": "stop", "ref": "761", "subway": "yes", "name:en": "Seongnam", "name:ja": "", "station": "", "wikidata": "", "wikipedia": "", "wheelchair": "", "train": "", "name:zh": "", "local_ref": "", "alt_name": "", "alt_name:en": "", "network": "", "addr:city": "", "addr:housenumber": "", "addr:street": "", "internet_access": "", "full_name": "", "bicycle": "", "description": "", "description:en": "", "light_rail": "", "name:ko-Latn": "", "tag": "", "alt_name:ko": "", "description:ja": "", "description:zh": "", "operator:en": "", "start_date": "2021-05-22", "layer": "", "loc_name": "", "construction": "", "platforms": "", "railway:signal:direction": "", "construction:railway": "" }, "geometry": { "type": "Point", "coordinates": [ 126.674630910547236, 37.506339495806941 ] } },
{ "type": "Feature", "properties": { "full_id": "n6185441878", "osm_id": "6185441878", "osm_type": "node", "name": "산곡", "name:ko": "산곡", "operator": "인천교통공사", "public_transport": "stop_position", "railway": "stop", "ref": "760", "subway": "yes", "name:en": "Sangok", "name:ja": "", "station": "", "wikidata": "", "wikipedia": "", "wheelchair": "", "train": "", "name:zh": "", "local_ref": "", "alt_name": "", "alt_name:en": "", "network": "", "addr:city": "", "addr:housenumber": "", "addr:street": "", "internet_access": "", "full_name": "", "bicycle": "", "description": "", "description:en": "", "light_rail": "", "name:ko-Latn": "", "tag": "", "alt_name:ko": "", "description:ja": "", "description:zh": "", "operator:en": "", "start_date": "2021-05-22", "layer": "", "loc_name": "", "construction": "", "platforms": "", "railway:signal:direction": "", "construction:railway": "" }, "geometry": { "type": "Point", "coordinates": [ 126.7036796, 37.5086158 ] } },
{ "type": "Feature", "properties": { "full_id": "n6185441877", "osm_id": "6185441877", "osm_type": "node", "name": "산곡", "name:ko": "산곡", "operator": "인천교통공사", "public_transport": "stop_position", "railway": "stop", "ref": "760", "subway": "yes", "name:en": "Sangok", "name:ja": "", "station": "", "wikidata": "", "wikipedia": "", "wheelchair": "", "train": "", "name:zh": "", "local_ref": "", "alt_name": "", "alt_name:en": "", "network": "", "addr:city": "", "addr:housenumber": "", "addr:street": "", "internet_access": "", "full_name": "", "bicycle": "", "description": "", "description:en": "", "light_rail": "", "name:ko-Latn": "", "tag": "", "alt_name:ko": "", "description:ja": "", "description:zh": "", "operator:en": "", "start_date": "2021-05-22", "layer": "", "loc_name": "", "construction": "", "platforms": "", "railway:signal:direction": "", "construction:railway": "" }, "geometry": { "type": "Point", "coordinates": [ 126.7036769, 37.5085533 ] } }
]
}
