{
"type": "FeatureCollection",
"name": "shanghai-line-9-phase-3-stops",
"crs": { "type": "name", "properties": { "name": "urn:ogc:def:crs:OGC:1.3:CRS84" } },
"features": [
{ "type": "Feature", "properties": { "full_id": "n621901825", "osm_id": "621901825", "osm_type": "node", "name": "Zuibaichi Park", "name:en": "Zuibaichi Park", "name:zh": "醉白池", "network": "", "public_transport": "stop_position", "railway": "", "subway": "yes", "wheelchair": "", "proposed:public_transport": "", "proposed:railway": "", "old_name": "", "name:ko": "", "access": "", "description": "", "light_rail": "", "amenity": "", "name:ja": "", "wikidata": "", "wikipedia": "", "highway": "", "traffic_signals": "", "entrance": "" }, "geometry": { "type": "Point", "coordinates": [ 121.224526, 31.0028368 ] } },
{ "type": "Feature", "properties": { "full_id": "n621901822", "osm_id": "621901822", "osm_type": "node", "name": "Songjiang Sports Center", "name:en": "Songjiang Sports Center", "name:zh": "松江体育中心", "network": "", "public_transport": "stop_position", "railway": "", "subway": "yes", "wheelchair": "", "proposed:public_transport": "", "proposed:railway": "", "old_name": "", "name:ko": "", "access": "", "description": "", "light_rail": "", "amenity": "", "name:ja": "", "wikidata": "", "wikipedia": "", "highway": "", "traffic_signals": "", "entrance": "" }, "geometry": { "type": "Point", "coordinates": [ 121.2262839, 31.0179935 ] } },
{ "type": "Feature", "properties": { "full_id": "n621901826", "osm_id": "621901826", "osm_type": "node", "name": "Songjiang South Railway Station", "name:en": "Songjiang South Railway Station", "name:zh": "松江南站", "network": "", "public_transport": "stop_position", "railway": "", "subway": "yes", "wheelchair": "", "proposed:public_transport": "", "proposed:railway": "", "old_name": "", "name:ko": "", "access": "", "description": "", "light_rail": "", "amenity": "", "name:ja": "", "wikidata": "", "wikipedia": "", "highway": "", "traffic_signals": "", "entrance": "" }, "geometry": { "type": "Point", "coordinates": [ 121.2266151, 30.9864446 ] } }
]
}
