{
"type": "FeatureCollection",
"name": "shenzhen-line-13-southern-extension-stops",
"crs": { "type": "name", "properties": { "name": "urn:ogc:def:crs:OGC:1.3:CRS84" } },
"features": [
{ "type": "Feature", "properties": { "full_id": null, "osm_id": null, "osm_type": null, "name": "Sunrise Amphitheatre", "name:en": "Sunrise Amphitheatre", "name:zh": null, "name:zh-Hant": null, "network": null, "operator": null, "public_transport": null, "railway": null, "subway": null, "website": null, "platforms": null, "station": null, "wikidata": null, "name:ru": null, "wheelchair": null, "construction": null, "wikipedia": null, "bus": null, "highway": null, "shelter": null, "train": null, "name:zh-Hans": null, "name:zh_pinyin": null, "access": null, "description": null, "traffic_signals": null, "traffic_signals:direction": null }, "geometry": { "type": "Point", "coordinates": [ 113.947285148363989, 22.503551828939958 ] } },
{ "type": "Feature", "properties": { "full_id": "n1947291248", "osm_id": "1947291248", "osm_type": "node", "name": "Dongjiaotou", "name:en": "Dongjiaotou", "name:zh": "东角头", "name:zh-Hant": "", "network": "", "operator": "", "public_transport": "stop_position", "railway": "", "subway": "yes", "website": "", "platforms": "", "station": "", "wikidata": "", "name:ru": "", "wheelchair": "", "construction": "", "wikipedia": "", "bus": "", "highway": "", "shelter": "", "train": "", "name:zh-Hans": "", "name:zh_pinyin": "", "access": "", "description": "", "traffic_signals": "", "traffic_signals:direction": "" }, "geometry": { "type": "Point", "coordinates": [ 113.9264154, 22.489132 ] } },
{ "type": "Feature", "properties": { "full_id": null, "osm_id": null, "osm_type": null, "name": "Opera House (location may change)", "name:en": "Opera House (location may change)", "name:zh": null, "name:zh-Hant": null, "network": null, "operator": null, "public_transport": null, "railway": null, "subway": null, "website": null, "platforms": null, "station": null, "wikidata": null, "name:ru": null, "wheelchair": null, "construction": null, "wikipedia": null, "bus": null, "highway": null, "shelter": null, "train": null, "name:zh-Hans": null, "name:zh_pinyin": null, "access": null, "description": null, "traffic_signals": null, "traffic_signals:direction": null }, "geometry": { "type": "Point", "coordinates": [ 113.938492267281717, 22.490237387811565 ] } }
]
}
