{
"type": "FeatureCollection",
"name": "tianjin-m3-phase-2-stops",
"crs": { "type": "name", "properties": { "name": "urn:ogc:def:crs:OGC:1.3:CRS84" } },
"features": [
{ "type": "Feature", "properties": { "full_id": "n3279351946", "osm_id": "3279351946", "osm_type": "node", "name": "Nanzhan", "name:en": "Nanzhan", "name:zh": "", "railway": "", "station": "", "wheelchair": "", "wikidata": "", "public_transport": "stop_position", "subway": "yes", "description:en": "", "entrance": "", "access": "", "description": "", "construction": "", "train": "" }, "geometry": { "type": "Point", "coordinates": [ 117.0557934, 39.0558899 ] } },
{ "type": "Feature", "properties": { "full_id": "n3824094438", "osm_id": "3824094438", "osm_type": "node", "name": "Xuefugongyequ", "name:en": "Xuefugongyequ", "name:zh": "", "railway": "station", "station": "subway", "wheelchair": "", "wikidata": "Q15922476", "public_transport": "station", "subway": "yes", "description:en": "Xuefu Industrial Zone", "entrance": "", "access": "", "description": "", "construction": "", "train": "" }, "geometry": { "type": "Point", "coordinates": [ 117.0721867, 39.0707249 ] } },
{ "type": "Feature", "properties": { "full_id": "n3824093643", "osm_id": "3824093643", "osm_type": "node", "name": "Yangwuzhuang", "name:en": "Yangwuzhuang", "name:zh": "", "railway": "station", "station": "subway", "wheelchair": "", "wikidata": "Q15923284", "public_transport": "stop_position", "subway": "yes", "description:en": "", "entrance": "", "access": "", "description": "", "construction": "", "train": "" }, "geometry": { "type": "Point", "coordinates": [ 117.0632597, 39.067129 ] } }
]
}
